alchemyst_langchain/__init__.py
alchemyst_langchain/examples/memory-examples.py
alchemyst_langchain/memory/__init__.py
alchemyst_langchain-0.1.0.dist-info/METADATA
alchemyst_langchain-0.1.0.dist-info/WHEEL
alchemyst_langchain-0.1.0.dist-info/top_level.txt
alchemyst_langchain-0.1.0.dist-info/RECORD
