Metadata-Version: 2.4
Name: alchemyst-langchain
Version: 0.1.0
Summary: Persistent memory integration for LangChain powered by Alchemyst AI
Author-email: Alchemyst <anuran@getalchemystai.com>
License: MIT
Requires-Python: >=3.10
Requires-Dist: requests>=2.31
Requires-Dist: langchain-core>=0.1.0
Requires-Dist: alchemystai>=0.10.0
Provides-Extra: dev
Requires-Dist: pytest>=7.0; extra == "dev"
Requires-Dist: pytest-cov>=4.0; extra == "dev"
Requires-Dist: responses>=0.23; extra == "dev"
Requires-Dist: build>=0.10; extra == "dev"
Requires-Dist: twine>=4.0; extra == "dev"
Requires-Dist: ruff>=0.1.0; extra == "dev"
Requires-Dist: mypy>=1.0; extra == "dev"
Requires-Dist: python-semantic-release>=9.0.0; extra == "dev"
Requires-Dist: python-dotenv; extra == "dev"
